{
    "网格交易示例表": "512980(传媒)",
    "最新时间": "2025-4-10",
    "网格交易数据": [
      {
        "网格种类": "小网",
        "档位": 1.00,
        "买入触发价": ["0.778", "0.782"],
        "买入价": ["0.774", "0.776"],
        "买入金额": ["11005", "14200"],
        "入股数": ["14200", "14200"],
        "卖出触发价": ["0.846", "0.850"],
        "卖出价": ["0.852", "0.854"],
        "出股数": "12900",
        "卖出金额": "11004"
      },
      {
        "网格种类": "小网",
        "档位": 0.90,
        "买入触发价": ["0.701", "0.705"],
        "买入价": ["0.697", "0.699"],
        "买入金额": ["11028", "15800"],
        "入股数": ["15800", "15800"],
        "卖出触发价": [],
        "卖出价": [],
        "出股数": "",
        "卖出金额": ""
      },
      {
        "网格种类": "小网",
        "档位": 0.77,
        "买入触发价": ["0.601", "0.605"],
        "买入价": ["0.597", "0.599"],
        "买入金额": ["12319", "20600"],
        "入股数": ["20600", "20600"],
        "卖出触发价": [],
        "卖出价": [],
        "出股数": "",
        "卖出金额": ""
      },
      {
        "利润": {
          "卖出触发价": ["1.048", "1.052"],
          "卖出价": ["1.054", "1.056"],
          "出股数": "8000",
          "卖出金额": "8440",
          "备注": "卖出前剩余36800股"
        }
      }
    ],
    "交易记录": [
      {
        "日期": "2021-07-28",
        "交易金额": "12086.2",
        "实际交易价格": "0.679",
        "交易股数": "17800",
        "收益": "",
        "收益率": ""
      },
      {
        "日期": "2021-09-08",
        "交易金额": "-11470",
        "实际交易价格": "0.740",
        "交易股数": "-15500",
        "收益": "1085.8",
        "收益率": "8.98%"
      },
      {
        "日期": "2021-10-27",
        "交易金额": "12086.2",
        "实际交易价格": "0.679",
        "交易股数": "17800",
        "收益": "",
        "收益率": ""
      },
      {
        "日期": "2021-11-05",
        "交易金额": "-11100",
        "实际交易价格": "0.740",
        "交易股数": "-15000",
        "收益": "1085.8",
        "收益率": "8.98%"
      },
      {
        "日期": "2021-07-26",
        "交易金额": "11396.0",
        "实际交易价格": "0.740",
        "交易股数": "15400",
        "收益": "",
        "收益率": ""
      },
      {
        "日期": "2021-11-16",
        "交易金额": "-10880.0",
        "实际交易价格": "0.800",
        "交易股数": "-13600",
        "收益": "924.0",
        "收益率": "8.11%"
      },
      {
        "日期": "2021-11-29",
        "交易金额": "11396.0",
        "实际交易价格": "0.740",
        "交易股数": "15400",
        "收益": "",
        "收益率": ""
      },
      {
        "日期": "2021-12-13",
        "交易金额": "-10960.0",
        "实际交易价格": "0.800",
        "交易股数": "-13700",
        "收益": "924.0",
        "收益率": "8.11%"
      },
      {
        "日期": "2021-03-15",
        "交易金额": "10480.0",
        "实际交易价格": "0.800",
        "交易股数": "13100",
        "收益": "",
        "收益率": ""
      },
      {
        "日期": "2021-12-31",
        "交易金额": "-10234.0",
        "实际交易价格": "0.860",
        "交易股数": "-11900",
        "收益": "786.0",
        "收益率": "7.50%"
      },
      {
        "日期": "2022-04-25",
        "交易金额": "13305.6",
        "实际交易价格": "0.576",
        "交易股数": "23100",
        "收益": "",
        "收益率": ""
      },
      {
        "日期": "2023-02-07",
        "交易金额": "-10524.5",
        "实际交易价格": "0.679",
        "交易股数": "-15500",
        "收益": "2379.3",
        "收益率": "17.88%"
      },
      {
        "日期": "2022-03-08",
        "交易金额": "12086.2",
        "实际交易价格": "0.679",
        "交易股数": "17800",
        "收益": "",
        "收益率": ""
      },
      {
        "日期": "2023-03-20",
        "交易金额": "-10635.8",
        "实际交易价格": "0.749",
        "交易股数": "-14200",
        "收益": "1246.0",
        "收益率": "10.31%"
      },
      {
        "日期": "2022-01-27",
        "交易金额": "11396.0",
        "实际交易价格": "0.740",
        "交易股数": "15400",
        "收益": "",
        "收益率": ""
      },
      {
        "日期": "2023-03-24",
        "交易金额": "-10960.0",
        "实际交易价格": "0.800",
        "交易股数": "-13700",
        "收益": "924.0",
        "收益率": "8.11%"
      },
      {
        "日期": "2022-01-24",
        "交易金额": "10720.0",
        "实际交易价格": "0.800",
        "交易股数": "13400",
        "收益": "",
        "收益率": ""
      },
      {
        "日期": "2023-04-03",
        "交易金额": "-10492.0",
        "实际交易价格": "0.860",
        "交易股数": "-12200",
        "收益": "804.0",
        "收益率": "7.50%"
      },
      {
        "日期": "2020-12-16",
        "交易金额": "10062.0",
        "实际交易价格": "0.860",
        "交易股数": "11700",
        "收益": "",
        "收益率": ""
      },
      {
        "日期": "2023-04-12",
        "交易金额": "-9660.0",
        "实际交易价格": "0.920",
        "交易股数": "-10500",
        "收益": "702.0",
        "收益率": "6.98%"
      },
      {
        "日期": "2023-10-20",
        "交易金额": "11028.4",
        "实际交易价格": "0.698",
        "交易股数": "15800",
        "收益": "",
        "收益率": ""
      },
      {
        "日期": "2023-11-07",
        "交易金额": "-11082.5",
        "实际交易价格": "0.775",
        "交易股数": "-14300",
        "收益": "1216.6",
        "收益率": "11.03%"
      },
      {
        "日期": "2024-02-05",
        "交易金额": "10998.0",
        "实际交易价格": "0.585",
        "交易股数": "18800",
        "收益": "",
        "收益率": ""
      },
      {
        "日期": "2024-02-20",
        "交易金额": "-12564.0",
        "实际交易价格": "0.698",
        "交易股数": "-18000",
        "收益": "2124.4",
        "收益率": "19.32%"
      },
      {
        "日期": "2023-12-25",
        "交易金额": "11028.4",
        "实际交易价格": "0.698",
        "交易股数": "15800",
        "收益": "",
        "收益率": ""
      },
      {
        "日期": "2024-03-19",
        "交易金额": "-11082.5",
        "实际交易价格": "0.775",
        "交易股数": "-14300",
        "收益": "1216.6",
        "收益率": "11.03%"
      },
      {
        "日期": "2024-07-08",
        "交易金额": "11016.8",
        "实际交易价格": "0.586",
        "交易股数": "18800",
        "收益": "",
        "收益率": ""
      },
      {
        "日期": "2024-09-30",
        "交易金额": "-12564.0",
        "实际交易价格": "0.698",
        "交易股数": "-18000",
        "收益": "2105.6",
        "收益率": "19.11%"
      },
      {
        "日期": "2024-04-15",
        "交易金额": "11028.4",
        "实际交易价格": "0.698",
        "交易股数": "15800",
        "收益": "",
        "收益率": ""
      },
      {
        "日期": "2024-10-08",
        "交易金额": "-11611.6",
        "实际交易价格": "0.812",
        "交易股数": "-14300",
        "收益": "1801.2",
        "收益率": "16.33%"
      },
      {
        "日期": "2024-10-11",
        "交易金额": "11028.4",
        "实际交易价格": "0.698",
        "交易股数": "15800",
        "收益": "",
        "收益率": ""
      },
      {
        "日期": "2024-10-22",
        "交易金额": "-11082.5",
        "实际交易价格": "0.775",
        "交易股数": "-14300",
        "收益": "1216.6",
        "收益率": "11.03%"
      },
      {
        "日期": "2023-09-08",
        "交易金额": "11005.0",
        "实际交易价格": "0.775",
        "交易股数": "14200",
        "收益": "",
        "收益率": ""
      },
      {
        "日期": "2024-12-05",
        "交易金额": "-11003.7",
        "实际交易价格": "0.853",
        "交易股数": "-12900",
        "收益": "1107.6",
        "收益率": "10.06%"
      },
      {
        "日期": "2024-12-31",
        "交易金额": "11005.0",
        "实际交易价格": "0.775",
        "交易股数": "14200",
        "收益": "",
        "收益率": ""
      },
      {
        "日期": "2025-02-10",
        "交易金额": "-11003.7",
        "实际交易价格": "0.853",
        "交易股数": "-12900",
        "收益": "1107.6",
        "收益率": "10.06%"
      },
      {
        "日期": "2025-04-09",
        "交易金额": "11028.4",
        "实际交易价格": "0.698",
        "交易股数": "15800",
        "收益": "",
        "收益率": ""
      },
      {
        "日期": "2025-04-10",
        "交易金额": "-11082.5",
        "实际交易价格": "0.775",
        "交易股数": "-14300",
        "收益": "1216.6",
        "收益率": "11.03%"
      }
    ]
  } 